<thesaurus><entry><key>accuser</key><term>prosecutor</term><term>indicter</term></entry><entry><key>acolyte</key><term>disciple</term><term>novice</term><term>follower</term><term>servant</term><term>attendant</term><term>assistant</term><term>aid</term><term>helper</term><term>apprentice</term></entry><entry><key>African</key><term>dark-skinned</term><term>black</term></entry><entry><key>angel</key><term>seraph</term><term>cherub</term><term>covering cherub</term><term>putto</term><term>Cupid</term><term>Boston's Angel</term><term>Albion's Angel</term><term>spirit</term></entry><entry><key>assassin</key><term>murderer</term><term>slayer</term><term>killer</term></entry><entry><key>bard</key><term>singer</term><term>storyteller</term><term>Homer</term><term>laurels</term><term>poet</term></entry><entry><key>beadle</key><term>town-crier</term><term>herald</term><term>messenger</term><term>sexton</term></entry><entry><key>beggar</key><term>poor</term><term>panhandler</term><term>mendicant</term><term>homeless</term><term>supplicant</term><term>vagabond</term></entry><entry><key>bellman</key><term>town-crier</term><term>announcer</term></entry><entry><key>blacksmith</key><term>smith</term><term>smithy</term><term>artisan</term></entry><entry><key>cherub</key><term>angel</term><term>covering cherub</term><term>putto</term><term>Cupid</term><term>cherubim</term><term>spirit</term></entry><entry><key>child</key><term>children</term><term>infant</term><term>youth</term><term>baby</term><term>babe</term><term>toddler</term><term>kid</term><term>son</term><term>daughter</term><term>offspring</term><term>descendant</term><term>young</term><term>newborn</term></entry><entry><key>chimney sweeper</key><term>chimney sweep</term><term>sweep</term></entry><entry><key>corpse</key><term>body</term><term>dead</term><term>dead body</term><term>cadaver</term><term>skeleton</term><term>carcass</term><term>deceased</term></entry><entry><key>covering cherub</key><term>angel</term><term>cherub</term><term>cherubim</term><term>spirit</term></entry><entry><key>demon</key><term>ghost</term><term>daemon</term><term>evil spirit</term><term>spectre</term><term>incubus</term><term>succubus</term><term>fiend</term><term>imp</term></entry><entry><key>devil</key><term>Satan</term><term>Lucifer</term><term>demon</term><term>fiend</term><term>imp</term></entry><entry><key>disciple</key><term>acolyte</term><term>student</term><term>apprentice</term><term>follower</term></entry><entry><key>Druid</key><term>priest</term><term>magician</term><term>medium</term><term>wizard</term><term>oracle</term></entry><entry><key>emanation</key><term>effluence</term><term>issuance</term></entry><entry><key>fairy</key><term>fairies</term><term>faery</term><term>faerie</term><term>sprite</term><term>elf</term><term>nymph</term><term>spirit</term></entry><entry><key>family</key><term>household</term><term>kin</term><term>kindred</term><term>kinship</term><term>race</term><term>progeny</term></entry><entry><key>father</key><term>parent</term><term>patriarch</term><term>ancestor</term><term>priest</term><term>progenitor</term><term>sire</term><term>male</term></entry><entry><key>female</key><term>woman</term><term>lady</term><term>feminine</term><term>Female Will</term><term>nameless shadowy female</term></entry><entry><key>fetus</key><term>fetal</term><term>baby</term><term>infant</term><term>unborn</term><term>child</term></entry><entry><key>ghost</key><term>spirit</term><term>spectre</term><term>lemures</term><term>apparition</term><term>shade</term><term>phantom</term><term>specter</term></entry><entry><key>giant</key><term>behemoth</term><term>leviathan</term><term>ogre</term><term>colossus</term></entry><entry><key>group of figures</key><term>group</term><term>crowd</term></entry><entry><key>guard</key><term>watchman</term><term>soldier</term><term>sentry</term><term>sentinel</term></entry><entry><key>herald</key><term>messenger</term><term>beadle</term><term>trumpeter</term><term>harbinger</term><term>diplomat</term><term>ambassador</term></entry><entry><key>infant</key><term>child</term><term>baby</term><term>babe</term><term>youth</term><term>toddler</term><term>young</term><term>kid</term><term>son</term><term>daughter</term><term>offspring</term></entry><entry><key>jailor</key><term>warden</term><term>guard</term><term>watchman</term></entry><entry><key>king</key><term>royalty</term><term>ruler</term><term>monarch</term><term>sovereign</term><term>emperor</term><term>regent</term><term>majesty</term></entry><entry><key>knight</key><term>cavalier</term><term>chevalier</term><term>cavalry</term><term>soldier</term><term>warrior</term><term>paladin</term></entry><entry><key>lars</key></entry><entry><key>lemures</key><term>ghost</term><term>spirit</term><term>spectre</term><term>apparition</term><term>shade</term><term>phantom</term><term>specter</term></entry><entry><key>male</key><term>man</term><term>masculine</term></entry><entry><key>messenger</key><term>herald</term><term>beadle</term><term>courier</term><term>trumpeter</term><term>harbinger</term><term>diplomat</term><term>ambassador</term></entry><entry><key>mother</key><term>parent</term><term>matron</term><term>matriarch</term><term>matron Clay</term><term>female</term></entry><entry><key>nurse</key><term>nanny</term><term>nursemaid</term><term>caretaker</term></entry><entry><key>nymph</key><term>elf</term><term>fairy</term><term>dryad</term><term>naiad</term><term>sprite</term><term>faery</term><term>spirit</term></entry><entry><key>philosopher</key><term>scholar</term><term>sage</term><term>scientist</term><term>thinker</term></entry><entry><key>piper</key><term>flutist</term><term>flautist</term><term>musician</term></entry><entry><key>poet</key><term>bard</term><term>writer</term><term>maker</term><term>laurels</term><term>author</term></entry><entry><key>Pope</key><term>pontiff</term></entry><entry><key>priest</key><term>Druid</term><term>minister</term><term>prophet</term><term>pastor</term><term>father</term><term>cleric</term><term>bishop</term><term>cardinal</term><term>monk</term></entry><entry><key>priestess</key><term>prophetess</term><term>sibyl</term><term>oracle</term></entry><entry><key>prisoner</key><term>captive</term><term>hostage</term><term>convict</term><term>chained</term><term>Chain of Jealousy</term></entry><entry><key>prophet</key><term>priest</term><term>seer</term><term>prophetess</term><term>Druid</term><term>augur</term><term>clairvoyant</term><term>diviner</term><term>sibyl</term><term>medium</term><term>oracle</term></entry><entry><key>putto</key><term>angel</term><term>cherub</term><term>covering cherub</term><term>Cupid</term></entry><entry><key>queen</key><term>royalty</term><term>princess</term><term>monarch</term><term>ruler</term><term>sovereign</term><term>empress</term><term>regent</term></entry><entry><key>sailor</key><term>mariner</term></entry><entry><key>saint</key><term>stigmata</term><term>self-flagellant</term><term>martyr</term></entry><entry><key>scribe</key><term>writer</term><term>scholar</term><term>copier</term><term>transcriber</term></entry><entry><key>self-flagellant</key><term>stigmata</term></entry><entry><key>shepherd</key><term>herdsman</term><term>shepherdess</term></entry><entry><key>sibyl</key><term>prophetess</term><term>priestess</term><term>witch</term><term>medium</term><term>oracle</term><term>seer</term><term>augur</term><term>diviner</term></entry><entry><key>slave</key><term>servant</term><term>laborer</term><term>captive</term><term>vassal</term></entry><entry><key>slave owner</key><term>master</term><term>overseer</term></entry><entry><key>soldier</key><term>guard</term><term>warrior</term><term>fighter</term></entry><entry><key>spectre</key><term>ghost</term><term>spirit</term><term>apparition</term><term>shade</term><term>evil spirit</term><term>specter</term></entry><entry><key>spirit</key><term>ghost</term><term>spectre</term><term>shade</term><term>soul</term><term>apparition</term><term>phantom</term><term>specter</term></entry><entry><key>student</key><term>students</term><term>scholar</term><term>pupil</term><term>learner</term><term>apprentice</term><term>disciple</term><term>novice</term></entry><entry><key>traveler</key><term>journeyman</term><term>pilgrim</term><term>explorer</term><term>wanderer</term><term>wayfarer</term><term>adventurer</term><term>migrant</term><term>voyager</term></entry><entry><key>trumpeter</key><term>herald</term><term>musician</term><term>bugler</term><term>harbinger</term></entry><entry><key>victim</key><term>prey</term><term>defendant</term><term>sacrifice</term><term>sufferer</term></entry><entry><key>virgin</key><term>celibate</term><term>maiden</term><term>virginal</term><term>maid</term><term>girl</term><term>Virgin Mary</term></entry><entry><key>watchman</key><term>guard</term><term>soldier</term><term>guardian</term><term>bellman</term><term>sentry</term><term>sentinel</term><term>caretaker</term><term>keeper</term><term>ward</term><term>watcher</term><term>patrol</term></entry><entry><key>wrestler</key><term>combatant</term><term>fighter</term></entry><entry><key>Cupid</key><term>putto</term><term>cherub</term><term>angel</term><term>covering cherub</term></entry><entry><key>God</key><term>Ancient of days</term><term>deity</term><term>lord</term><term>almighty</term><term>father</term><term>creator</term><term>Jehovah</term><term>maker</term></entry><entry><key>Satan</key><term>devil</term><term>Lucifer</term><term>fiend</term><term>Antichrist</term></entry><entry><key>arm</key></entry><entry><key>arm at side</key></entry><entry><key>arm behind back</key></entry><entry><key>arm bent</key><term>arm bent upward</term><term>arm bent over shoulder</term></entry><entry><key>arm bent upward</key><term>arm bent</term></entry><entry><key>arm bent over shoulder</key><term>arm bent</term></entry><entry><key>arm braced</key></entry><entry><key>arm dangling</key></entry><entry><key>arm down</key><term>arm at side</term><term>arm dangling</term><term>arm reaching downward</term><term>arm on lap</term></entry><entry><key>arm drawn back</key></entry><entry><key>arm extended</key></entry><entry><key>arm on lap</key></entry><entry><key>arm raised</key><term>arm raised at 45 degrees</term><term>arm raised at 135 degrees</term><term>arm raised vertically</term><term>arm raised horizontally</term></entry><entry><key>arm raised at 45 degrees</key><term>arm raised</term></entry><entry><key>arm raised at 135 degrees</key><term>arm raised</term></entry><entry><key>arm raised horizontally</key><term>arm raised</term></entry><entry><key>arm raised vertically</key><term>arm raised</term></entry><entry><key>arm reaching between legs</key><term>arm reaching downward</term></entry><entry><key>arm reaching downward</key><term>arm down</term></entry><entry><key>arm resting</key></entry><entry><key>arm wrapped around body</key></entry><entry><key>arm wrapped around head</key></entry><entry><key>arms at side</key></entry><entry><key>arms bent</key><term>arms bent upward</term></entry><entry><key>arms bent upward</key><term>arms bent</term></entry><entry><key>arms braced</key></entry><entry><key>arms crossed</key></entry><entry><key>arms down</key></entry><entry><key>arms drawn back</key></entry><entry><key>arms on lap</key></entry><entry><key>arms extended</key></entry><entry><key>arms folded</key></entry><entry><key>arms raised</key><term>arms raised at 45 degrees</term><term>arms raised at 135 degrees</term><term>arms raised horizontally</term><term>arms raised vertically</term></entry><entry><key>arms raised at 45 degrees</key><term>arms raised</term></entry><entry><key>arms raised at 135 degrees</key><term>arms raised</term></entry><entry><key>arms raised horizontally</key><term>arms raised</term></entry><entry><key>arms raised vertically</key><term>arms raised</term></entry><entry><key>arms resting</key><term>hand resting</term></entry><entry><key>arms wrapped around body</key></entry><entry><key>arms wrapped around head</key></entry><entry><key>arms wrapped around knees</key><term>arms wrapped around body</term></entry><entry><key>bathing</key><term>washing</term><term>rinsing</term></entry><entry><key>batting</key><term>hitting</term><term>striking</term></entry><entry><key>bending backward</key></entry><entry><key>bending forward</key><term>leaning</term><term>hunched over</term><term>bowing</term></entry><entry><key>bending left</key><term>bending right</term><term>leaning</term></entry><entry><key>blessing</key><term>praying</term><term>glorifying</term><term>honoring</term></entry><entry><key>body horizontal</key><term>lying</term><term>supine</term><term>prone</term></entry><entry><key>bound</key><term>chained</term><term>restrained</term></entry><entry><key>bowing</key><term>bending forward</term><term>facing down</term></entry><entry><key>brain</key><term>mind</term><term>head</term></entry><entry><key>breaking</key><term>smashing</term><term>cracking</term><term>shattering</term><term>snapping</term><term>splitting</term><term>dividing</term><term>separating</term><term>parting</term><term>snapping</term><term>damaging</term></entry><entry><key>buried</key><term>interred</term><term>hidden</term></entry><entry><key>buttocks</key><term>rear</term><term>butt</term><term>behind</term><term>bottom</term><term>posterior</term></entry><entry><key>carrying</key><term>holding</term><term>bringing</term><term>bearing</term><term>conveying</term><term>hauling</term></entry><entry><key>casting</key><term>throwing</term><term>flinging</term><term>scattering</term><term>tossing</term></entry><entry><key>chest</key><term>breast</term><term>breasts</term><term>bosom</term><term>trunk</term><term>case</term></entry><entry><key>climbing</key><term>rising</term><term>climber</term><term>ascending</term><term>clambering</term></entry><entry><key>combing</key><term>comb</term><term>brush</term><term>straightening</term><term>smoothing</term><term>untangling</term></entry><entry><key>contracted</key><term>hunched over</term><term>reduced</term><term>shrunk</term><term>decreased</term></entry><entry><key>contrapposto</key><term>twisted</term><term>asymmetrical</term></entry><entry><key>cooking</key><term>baking</term><term>heating</term><term>brewing</term><term>preparing</term></entry><entry><key>copying</key><term>copy</term><term>replicating</term><term>transcribing</term></entry><entry><key>crawling</key><term>crawl</term><term>creeping</term></entry><entry><key>creating</key><term>drawing</term><term>writing</term><term>sculpting</term><term>forging</term><term>making</term><term>forming</term><term>shaping</term><term>composing</term><term>conceiving</term><term>building</term><term>begetting</term><term>originating</term></entry><entry><key>crouching</key><term>squatting</term><term>huddling</term><term>bending</term><term>ducking</term><term>hunching</term></entry><entry><key>crucified</key><term>stigmata</term><term>martyred</term><term>persecuted</term><term>killed</term></entry><entry><key>crying</key><term>weeping</term><term>howling</term><term>grieving</term><term>lamenting</term><term>wailing</term><term>sobbing</term></entry><entry><key>cutting</key><term>dividing</term><term>engraving</term><term>slicing</term><term>scoring</term><term>severing</term><term>bisecting</term></entry><entry><key>dancing</key><term>playing</term><term>dancer</term><term>jumping</term><term>leaping</term><term>frolicking</term></entry><entry><key>descending</key><term>falling</term><term>dropping</term><term>plummeting</term><term>plunging</term><term>declining</term><term>diving</term></entry><entry><key>dividing</key><term>measuring</term><term>bisecting</term><term>cleaving</term><term>halving</term><term>severing</term><term>splitting</term><term>sundering</term><term>unbinding</term></entry><entry><key>drawing</key><term>writing</term><term>artist</term><term>creating</term><term>designing</term><term>composing</term><term>depicting</term><term>sketching</term><term>portraying</term><term>painting</term></entry><entry><key>dreaming</key><term>sleeping</term><term>dream</term><term>imagining</term></entry><entry><key>drinking</key><term>swallowing</term></entry><entry><key>drowning</key><term>dying</term><term>sinking</term></entry><entry><key>dying</key><term>drowning</term><term>perishing</term></entry><entry><key>ear</key></entry><entry><key>embracing</key><term>holding</term><term>hugging</term><term>clasping</term><term>clutching</term></entry><entry><key>encircling</key><term>intertwined</term><term>circumscribing</term><term>surrounding</term><term>encompassing</term><term>enclosing</term></entry><entry><key>eyes closed</key></entry><entry><key>eyes down</key><term>eyes downcast</term></entry><entry><key>eyes raised</key></entry><entry><key>facing away</key><term>seen from behind</term><term>averted</term></entry><entry><key>facing down</key><term>bowing</term></entry><entry><key>facing forward</key></entry><entry><key>facing left</key></entry><entry><key>facing right</key></entry><entry><key>facing up</key></entry><entry><key>falling</key><term>falling backward</term><term>collapsing</term><term>descending</term></entry><entry><key>falling backward</key><term>falling</term><term>collapsing</term><term>descending</term></entry><entry><key>feet</key><term>feet touching</term></entry><entry><key>feet touching</key><term>feet</term></entry><entry><key>fighting</key><term>kicking</term><term>hitting</term><term>combating</term><term>wrestling</term><term>grappling</term><term>struggling</term></entry><entry><key>fingers</key><term>fingers spread</term></entry><entry><key>fingers spread</key><term>fingers</term></entry><entry><key>fist</key><term>punching</term><term>fists</term><term>hitting</term></entry><entry><key>fleeing</key><term>flee</term><term>escaping</term><term>flying</term><term>leaving</term></entry><entry><key>floating</key><term>hovering</term><term>rising</term><term>flying</term><term>ascending</term></entry><entry><key>flying</key><term>soaring</term><term>floating</term><term>hovering</term><term>ascending</term><term>rising</term><term>fleeing</term><term>gliding</term></entry><entry><key>giving</key><term>offering</term><term>presenting</term><term>bestowing</term><term>conveying</term><term>delivering</term><term>handing</term></entry><entry><key>giving birth</key><term>delivering</term><term>procreating</term><term>conceiving</term></entry><entry><key>hand</key></entry><entry><key>hand beside head</key></entry><entry><key>hand clutching head</key><term>head on hand</term></entry><entry><key>hand holding</key></entry><entry><key>hand on breasts</key></entry><entry><key>hand on face</key><term>hand covering face</term><term>hiding</term><term>concealing</term></entry><entry><key>hand on genitals</key></entry><entry><key>hand on ground</key><term>arm reaching downward</term></entry><entry><key>hand on knee</key><term>hand on knees</term></entry><entry><key>hand raised, palm down</key><term>palm down</term><term>palms down</term></entry><entry><key>hand raised, palm out</key><term>palm out</term><term>palms out</term></entry><entry><key>hand raised, palm up</key></entry><entry><key>hand resting</key><term>arms resting</term></entry><entry><key>hand under head</key></entry><entry><key>hands behind head</key><term>arms wrapped around head</term></entry><entry><key>hands beside head</key></entry><entry><key>hands clutching head</key></entry><entry><key>hands on ankles</key><term>arms reaching downward</term></entry><entry><key>hands on breasts</key></entry><entry><key>hands on face</key><term>covering face</term><term>hiding. concealing</term></entry><entry><key>hands on ground</key><term>arms reaching downward</term></entry><entry><key>hands on knees</key><term>hand on knee</term></entry><entry><key>hands raised, palms down</key></entry><entry><key>hands raised, palms out</key></entry><entry><key>hands raised, palms up</key></entry><entry><key>hands resting</key><term>arms resting</term></entry><entry><key>hands to ears</key><term>hands covering ears</term><term>plugging ears</term></entry><entry><key>hands together</key><term>hands folded</term><term>hands clasped</term><term>hand holding</term></entry><entry><key>hanging</key><term>noose</term><term>dangling</term><term>suspended</term></entry><entry><key>harvesting</key><term>harvest</term><term>gathering</term><term>reaping</term></entry><entry><key>head bent back</key><term>head up</term></entry><entry><key>head down</key><term>hunched over</term><term>facing down</term><term>bowing</term></entry><entry><key>head on arm</key><term>head on arms</term></entry><entry><key>head on arms</key><term>head on arm</term><term>hand on face</term><term>hand clutching head</term></entry><entry><key>head on hand</key><term>hand on face</term><term>hand clutching head</term></entry><entry><key>head on hands</key><term>head on hand</term><term>hand on face</term><term>hand clutching head</term></entry><entry><key>head on knee</key><term>contracted</term><term>legs drawn up</term><term>hunched over</term><term>bending forward</term><term>huddled</term></entry><entry><key>head on knees</key><term>hunched over</term><term>bending forward</term><term>huddled</term></entry><entry><key>head on shoulder</key></entry><entry><key>head toward viewer</key><term>facing forward</term></entry><entry><key>head up</key><term>facing up</term></entry><entry><key>heads, multiple</key><term>group of figures</term><term>crowd</term></entry><entry><key>hitting</key><term>fighting</term><term>striking</term></entry><entry><key>holding</key><term>carrying</term><term>supporting</term><term>clasping</term><term>clutching</term><term>embracing</term><term>gripping</term><term>possessing</term></entry><entry><key>hovering</key><term>floating</term><term>rising</term><term>flying</term><term>soaring</term><term>drifting</term></entry><entry><key>howling</key><term>crying</term><term>grieving</term><term>sorrowing</term><term>wailing</term><term>screaming</term><term>lamenting</term></entry><entry><key>huddled</key><term>hunched over</term><term>bending forward</term><term>stooped</term><term>huddling</term><term>crouching</term></entry><entry><key>hunched over</key><term>huddled</term><term>contracted</term><term>bending forward</term><term>huddling</term><term>crouching</term></entry><entry><key>kicking</key></entry><entry><key>kissing</key></entry><entry><key>kneeling</key><term>praying</term></entry><entry><key>knee</key><term>knees</term></entry><entry><key>knees</key><term>knee</term></entry><entry><key>leading</key><term>leader</term><term>directing</term><term>conveying</term><term>guiding</term><term>shepherding</term><term>commanding</term><term>supervising</term><term>governing</term></entry><entry><key>leaning</key><term>bending left</term><term>arm braced</term><term>resting</term></entry><entry><key>leaping</key><term>dancing</term><term>lunging</term><term>playing</term><term>jumping</term><term>frolicking</term></entry><entry><key>left foot</key></entry><entry><key>leg</key></entry><entry><key>leg bent at knee</key><term>leg bent forward</term><term>leg bent</term></entry><entry><key>leg bent forward</key><term>leg bent at knee</term><term>leg bent</term></entry><entry><key>leg dangling</key></entry><entry><key>leg drawn up</key></entry><entry><key>leg extended backward</key></entry><entry><key>legs bent</key><term>leg bent forward</term><term>leg extended backward</term><term>leg bent at knee</term><term>legs drawn up</term><term>leg drawn up</term></entry><entry><key>legs crossed</key></entry><entry><key>legs dangling</key></entry><entry><key>legs drawn up</key></entry><entry><key>legs extended</key></entry><entry><key>legs spread</key></entry><entry><key>legs together</key></entry><entry><key>lifting</key><term>supporting</term><term>carrying</term><term>holding</term></entry><entry><key>limp</key><term>stagger</term><term>flag</term><term>falter</term></entry><entry><key>listening</key><term>hearing</term></entry><entry><key>looking</key><term>beholding</term><term>seeing</term><term>observing</term><term>watching</term></entry><entry><key>lunging</key><term>leaping</term><term>pouncing</term><term>diving</term></entry><entry><key>lying</key><term>body horizontal</term><term>prone</term><term>supine</term><term>reclining</term></entry><entry><key>lying on side</key></entry><entry><key>measuring</key><term>dividing</term><term>demarcating</term><term>portioning</term><term>determining</term></entry><entry><key>mourning</key><term>grief</term><term>crying</term><term>sorrowing</term><term>lamenting</term></entry><entry><key>mouth open</key></entry><entry><key>palm down</key><term>[hand raised</term><term>palm down]</term></entry><entry><key>palm out</key><term>[hand raised</term><term>palm out]</term></entry><entry><key>palm vertical</key><term>palms vertical</term></entry><entry><key>palms down</key><term>[hands raised</term><term>palms down]</term></entry><entry><key>palms facing viewer</key><term>palms vertical</term></entry><entry><key>palms out</key><term>[hands raised</term><term>palms out]</term></entry><entry><key>palms up</key><term>hands raised</term><term>palms up</term></entry><entry><key>palms vertical</key><term>palm vertical</term></entry><entry><key>petrifying</key><term>solidifying</term><term>hardening</term><term>rigid</term></entry><entry><key>planting</key><term>ploughing</term><term>sowing</term><term>growing</term></entry><entry><key>playing</key><term>dancing</term><term>leaping</term><term>frolicking</term></entry><entry><key>plowing</key><term>planting</term><term>tilling</term></entry><entry><key>pointing</key><term>reaching</term><term>indicating</term></entry><entry><key>praying</key><term>blessing</term><term>kneeling</term><term>supplicating</term></entry><entry><key>prone</key><term>lying</term><term>body horizontal</term><term>supine</term><term>reclining</term></entry><entry><key>pulling</key><term>hauling</term></entry><entry><key>pursuing</key><term>chasing</term><term>following</term></entry><entry><key>pushing</key><term>shoving</term><term>thrusting</term></entry><entry><key>reaching</key><term>extending</term></entry><entry><key>reading</key><term>reader</term><term>studying</term></entry><entry><key>reclining</key><term>lying</term><term>body horizontal</term><term>supine</term><term>prone</term></entry><entry><key>rescuing</key><term>resuscitating</term><term>saving</term></entry><entry><key>resuscitating</key><term>rescuing</term><term>reviving</term><term>saving</term><term>awakening</term><term>resurrecting</term><term>rejuvenating</term><term>restoring</term><term>revitalizing</term></entry><entry><key>riding</key><term>straddling</term></entry><entry><key>right foot</key></entry><entry><key>rigid</key><term>petrifying</term><term>stiff</term><term>hard</term><term>petrified</term><term>ossified</term></entry><entry><key>rising</key><term>hovering</term><term>floating</term><term>flying</term><term>ascending</term><term>soaring</term></entry><entry><key>rocking</key><term>rocker</term><term>cradle</term><term>cradling</term></entry><entry><key>running</key><term>fleeing</term><term>escaping</term><term>hastening</term><term>sprinting</term></entry><entry><key>sailing</key><term>sailor</term><term>voyaging</term></entry><entry><key>scalp</key><term>scalping</term></entry><entry><key>sculpting</key><term>sculptor</term><term>forming</term><term>shaping</term><term>making</term></entry><entry><key>seen from behind</key><term>facing away</term></entry><entry><key>serpent-coiled</key><term>coil</term><term>serpentine</term></entry><entry><key>sheathing</key><term>winding</term><term>enveloping</term><term>covering</term><term>encasing</term><term>enclosing</term><term>wrapping</term></entry><entry><key>shooting</key><term>emitting</term><term>firing</term><term>expeling</term></entry><entry><key>shoulder</key><term>shoulders</term></entry><entry><key>shoulders</key><term>shoulder</term></entry><entry><key>singing</key><term>bard</term><term>singer</term></entry><entry><key>sitting</key><term>sitting-crossed legged</term></entry><entry><key>sitting crossed-legged</key><term>sitting</term></entry><entry><key>sleeping</key><term>dreaming</term><term>asleep</term><term>resting</term><term>slumbering</term></entry><entry><key>smiling</key><term>smile</term><term>grinning</term><term>laughing</term></entry><entry><key>speaking</key><term>speech</term><term>talking</term><term>saying</term><term>telling</term><term>conversing</term><term>communicating</term><term>voicing</term></entry><entry><key>spine</key><term>nerves</term><term>vertebrae</term></entry><entry><key>spinning</key><term>revolving</term><term>turning</term><term>rotating</term><term>whirling</term><term>twisting</term></entry><entry><key>squatting</key><term>crouching</term><term>huddling</term><term>bending</term><term>ducking</term><term>hunching</term></entry><entry><key>standing</key></entry><entry><key>straddling</key><term>riding</term><term>mounting</term></entry><entry><key>strangling</key><term>choking</term><term>suffocating</term><term>throttling</term><term>killing</term></entry><entry><key>stretched</key><term>twisted</term><term>extended</term><term>elongated</term><term>spread</term></entry><entry><key>striding</key><term>walking</term><term>traveling</term></entry><entry><key>stroking</key><term>touching</term><term>caressing</term><term>brushing</term><term>soothing</term></entry><entry><key>supine</key><term>lying</term><term>body horizontal</term><term>facing up</term><term>prone</term><term>reclining</term></entry><entry><key>supplicating</key><term>praying</term><term>appealing</term><term>begging</term><term>beseeching</term><term>petitioning</term><term>soliciting</term></entry><entry><key>supporting</key><term>lifting</term><term>bracing</term><term>carrying</term><term>upholding</term></entry><entry><key>swimming</key><term>swimmer</term></entry><entry><key>taking</key><term>reaching</term><term>giving</term><term>getting</term><term>grasping</term><term>receiving</term></entry><entry><key>teaching</key><term>teacher</term><term>educating</term><term>advising</term><term>directing</term><term>explaining</term><term>instructing</term><term>training</term><term>guiding</term></entry><entry><key>thigh</key></entry><entry><key>throwing</key><term>casting</term><term>tossing</term></entry><entry><key>tiptoe</key></entry><entry><key>touching</key><term>stroking</term></entry><entry><key>twisted</key><term>stretched</term><term>spiraled</term><term>twined</term><term>braided</term><term>woven</term></entry><entry><key>upside down</key><term>upside-down</term><term>inverted</term><term>overturned</term></entry><entry><key>vegetating</key><term>metamorphosis</term><term>growing</term><term>blooming</term><term>burgeoning</term><term>blossoming</term></entry><entry><key>walking</key><term>striding</term><term>traveling</term></entry><entry><key>weaving</key><term>weaver</term><term>woven</term><term>braiding</term><term>entwining</term><term>twisting</term><term>winding</term><term>interlacing</term><term>twining</term><term>spiraling</term></entry><entry><key>whipping</key><term>whip</term><term>beating</term><term>punishing</term><term>flagellating</term><term>striking</term></entry><entry><key>winding</key><term>winding sheet</term><term>curving</term><term>twisting</term><term>weaving</term><term>spiraling</term><term>entwining</term><term>twining</term><term>curling</term><term>coiling</term></entry><entry><key>writing</key><term>writer</term><term>text</term><term>composing</term><term>copying</term><term>creating</term><term>inscribing</term></entry><entry><key>abdomen</key><term>stomach</term><term>belly</term><term>midriff</term><term>midsection</term></entry><entry><key>anger</key><term>rage</term><term>fury</term><term>ire</term><term>wrath</term></entry><entry><key>armor</key><term>shield</term><term>helmet</term><term>breastplate</term><term>mail</term><term>chain mail</term></entry><entry><key>aura</key><term>halo</term><term>beams of light</term><term>light</term><term>glow</term><term>radiance</term><term>radiant</term><term>emanation</term><term>atmosphere</term></entry><entry><key>bald</key><term>hairless</term><term>shaven</term><term>shorn</term><term>bare</term></entry><entry><key>band</key><term>stripe</term><term>mark</term></entry><entry><key>bat-eared</key></entry><entry><key>bat-winged</key><term>winged</term></entry><entry><key>beard</key><term>mustache (not listed as a characteristic)</term><term>sideburns</term></entry><entry><key>belt</key><term>sash</term><term>girdle</term><term>strap</term></entry><entry><key>blind</key><term>eyes closed</term><term>sightless</term><term>unseeing</term></entry><entry><key>blindfolded</key><term>masked</term><term>blind</term><term>blind fold</term><term>blind folded (separate words)</term><term>blindered</term><term>veiled</term></entry><entry><key>boots</key><term>shoes</term></entry><entry><key>breasts</key><term>breast</term><term>chest</term><term>bosom</term></entry><entry><key>breeches</key><term>pants</term><term>trousers</term><term>shorts</term></entry><entry><key>brooch</key><term>jewelry</term></entry><entry><key>buckle</key><term>clasp</term></entry><entry><key>bun</key><term>hair up</term><term>hair pulled back</term></entry><entry><key>cannibalism</key><term>cannibals</term><term>anthropophagy</term></entry><entry><key>chained</key><term>shackle</term><term>prisoner</term><term>bound</term><term>fettered</term><term>manacled</term><term>restrained</term><term>tied</term><term>shackled</term><term>tethered</term></entry><entry><key>cloak</key><term>coat</term><term>overcoat</term><term>robe</term><term>mantle</term><term>jacket</term><term>cape</term><term>shawl</term><term>veil</term><term>shroud</term></entry><entry><key>cloth</key><term>fabric</term><term>fiber</term><term>fibre</term><term>fibres</term><term>textile</term><term>material</term><term>sheet</term><term>swatch</term><term>drapery</term><term>curtain</term></entry><entry><key>coat</key><term>cloak</term><term>robe</term><term>overcoat</term><term>jacket</term></entry><entry><key>curly hair</key><term>curls</term><term>locks</term><term>wavy hair</term></entry><entry><key>dark-skinned</key><term>black</term><term>African</term></entry><entry><key>dead</key><term>corpse</term><term>deceased</term><term>dead body</term><term>death</term><term>lifeless</term><term>cadaver</term></entry><entry><key>despair</key><term>sorrow</term><term>grief</term><term>mourning</term><term>sadness</term><term>depression</term><term>melancholy</term><term>sad</term><term>hopelessness</term><term>gloom</term><term>misery</term><term>desperation</term><term>dejection</term><term>pain</term></entry><entry><key>disease</key><term>illness</term><term>plague</term><term>pestilence</term><term>epidemic</term><term>ailment</term><term>affliction</term><term>sickness</term><term>malady</term></entry><entry><key>disembowelment</key><term>evisceration</term><term>eviscerate</term><term>disembowel</term></entry><entry><key>dismembered</key><term>dismember</term><term>amputate</term><term>amputated</term><term>mutilate</term><term>mutilated</term><term>sever</term><term>severed</term><term>cut</term></entry><entry><key>drapery</key><term>cloth</term><term>curtain</term><term>shroud</term><term>sheet</term><term>fabric</term></entry><entry><key>drowned</key><term>dead</term><term>asphyxiated</term><term>submerged</term><term>killed</term><term>suffocated</term></entry><entry><key>ear</key></entry><entry><key>eating</key><term>feeding</term><term>chewing</term><term>swallowing</term><term>grazing</term><term>feasting</term><term>dining</term><term>eat</term><term>consuming</term><term>biting</term><term>devouring</term><term>grazing</term></entry><entry><key>ecstasy</key><term>pleasure</term><term>exhilaration</term><term>bliss</term><term>delight</term><term>joy</term><term>rapture</term><term>euphoria</term><term>happiness</term><term>elation</term><term>exaltation</term></entry><entry><key>emaciated</key><term>famine</term><term>starved</term><term>starving</term><term>hungry</term><term>hunger</term><term>poverty</term><term>skeleton</term><term>rib</term><term>gaunt</term><term>skinny</term><term>famished</term><term>lean</term></entry><entry><key>erotic</key><term>sex</term><term>sexual</term><term>carnal</term><term>sensual</term><term>impassioned</term></entry><entry><key>exhausted</key><term>tired</term><term>weary</term><term>fatigued</term><term>fatigue</term><term>sleepy</term></entry><entry><key>face</key><term>features</term><term>countenance</term><term>visage</term><term>profile</term></entry><entry><key>famine</key><term>hunger</term><term>emaciated</term><term>starvation</term><term>starve</term><term>misery</term><term>poverty</term></entry><entry><key>fainting</key><term>faint</term><term>swoon</term><term>collapse</term><term>collapsing</term><term>falling</term><term>go limp</term></entry><entry><key>fear</key><term>terror</term><term>dread</term><term>fright</term><term>frightened</term><term>horror</term><term>alarm</term><term>apprehension</term><term>terror</term><term>unease</term><term>worry</term><term>despair</term></entry><entry><key>fibres</key><term>cloth</term><term>fabric</term><term>fiber</term><term>fibre</term></entry><entry><key>flame-like hair</key><term>spiky</term><term>hair standing on end</term></entry><entry><key>flesh</key><term>skin</term><term>body</term><term>corporeal</term></entry><entry><key>forelock</key><term>long hair</term><term>hair</term><term>fore-lock</term><term>fore lock</term></entry><entry><key>genitals</key><term>loincloth</term><term>loins</term><term>womb</term><term>genitalia</term><term>vagina</term><term>penis</term><term>genitalia</term><term>privates</term></entry><entry><key>gown</key><term>robe</term><term>dress</term><term>frock</term></entry><entry><key>grief</key><term>mourning</term><term>sorrow</term><term>despair</term><term>sadness</term><term>bereavement</term><term>melancholy</term><term>suffering</term><term>misery</term><term>woe</term><term>pain</term></entry><entry><key>head</key><term>forehead</term><term>crown</term><term>cheek</term><term>cheeks</term><term>face</term></entry><entry><key>headless</key><term>decapitated</term><term>acephalic</term></entry><entry><key>hair</key><term>locks</term><term>tresses</term></entry><entry><key>hair standing on end</key><term>spiky</term><term>flamelike</term></entry><entry><key>halo</key><term>aura</term><term>radiance</term><term>saint</term><term>beams of light</term><term>light</term></entry><entry><key>hem</key><term>fringe</term><term>skirt</term></entry><entry><key>hood</key><term>hooded</term><term>cowl</term><term>cowled</term></entry><entry><key>intestine</key><term>entrails</term><term>viscera</term><term>gut</term><term>digestive tract</term><term>bowels</term></entry><entry><key>lap</key><term>thigh</term><term>knee</term><term>knees</term><term>arm on lap</term><term>arms on lap</term></entry><entry><key>laurels</key><term>bay</term><term>bays</term><term>laurel</term><term>laurel wreath</term><term>laurel branch</term><term>laureate</term></entry><entry><key>loincloth</key><term>loin cloth</term><term>loin-cloth</term></entry><entry><key>long hair</key><term>tresses</term><term>hair</term></entry><entry><key>meekness</key><term>meek</term><term>humility</term><term>humble</term><term>docility</term><term>gentle</term><term>gentleness</term><term>submission</term><term>submissive</term><term>timidity</term><term>modesty</term></entry><entry><key>melancholy</key><term>despair</term><term>sorrow</term><term>sadness</term><term>mourning</term><term>grief</term><term>depression</term><term>sad</term><term>gloomy</term><term>miserable</term><term>dismal</term><term>dejected</term></entry><entry><key>muscular</key><term>strong</term><term>muscle</term><term>powerful</term><term>athletic</term><term>tough</term><term>vigorous</term><term>mighty</term></entry><entry><key>nerves</key><term>nerve</term><term>nervous system</term><term>sinew</term><term>fascicle</term></entry><entry><key>nude</key><term>naked</term><term>stripped</term><term>bare</term><term>undressed</term><term>undraped</term></entry><entry><key>old</key><term>elderly</term><term>elder</term><term>ancient</term><term>aged</term></entry><entry><key>pain</key><term>suffering</term><term>anguish</term><term>hurt</term><term>torture</term><term>agony</term><term>torment</term><term>affliction</term><term>misery</term></entry><entry><key>pants</key><term>trousers</term></entry><entry><key>partly nude</key><term>partially nude</term><term>partly naked</term><term>partially naked</term><term>undraped</term><term>scantly dressed</term><term>half naked</term><term>bare breasted</term><term>bare chested</term><term>bare shouldered</term></entry><entry><key>pity</key><term>compassion</term><term>sympathy</term><term>pitiful</term><term>pathetic</term><term>benevolence</term><term>mercy</term></entry><entry><key>ribs</key><term>skeleton</term><term>bone</term><term>bones</term><term>side</term><term>rib cage</term><term>ribcage</term></entry><entry><key>robe</key><term>cloak</term><term>gown</term><term>robes</term><term>regalia</term><term>dress</term><term>garment</term></entry><entry><key>sacrifice</key><term>offering</term><term>burnt offering</term><term>libation</term><term>penance</term></entry><entry><key>sandal</key><term>shoe</term></entry><entry><key>scarf</key><term>head scarf</term><term>cravat</term><term>neckerchief</term><term>tie</term><term>sash</term><term>shawl</term></entry><entry><key>severed head</key><term>dismembered</term><term>decapitated</term><term>headless</term><term>decapitation</term></entry><entry><key>shackled</key><term>chained</term><term>bound</term><term>fettered</term><term>captive</term><term>chain</term><term>shackle</term><term>restrained</term><term>manacled</term></entry><entry><key>shirt</key><term>cloak</term><term>vest</term><term>jacket</term><term>blouse</term></entry><entry><key>shoes</key><term>boot</term><term>boots</term><term>shoe</term><term>shod</term><term>slipper</term><term>sandal</term></entry><entry><key>short hair</key><term>cropped hair</term></entry><entry><key>shroud</key><term>drapery</term><term>pall</term><term>winding sheet</term><term>veil</term><term>curtain</term><term>covering</term><term>cloak</term></entry><entry><key>sinews</key><term>veins</term><term>nerves</term><term>muscles</term><term>muscle</term><term>sinew</term><term>tendon</term><term>ligament</term><term>fibres</term><term>fiber</term><term>cord</term><term>joint</term></entry><entry><key>skeleton</key><term>bone</term><term>bones</term><term>rib</term><term>skeletal</term><term>rib cage</term><term>cadaver</term><term>corpse</term><term>skull</term></entry><entry><key>skirt</key><term>hem</term><term>dress</term><term>garment</term></entry><entry><key>skull</key><term>head</term><term>skeleton</term><term>corpse</term><term>cadaver</term><term>death's head</term><term>momento mori</term><term>dead</term><term>death</term><term>cranium</term></entry><entry><key>snake-like</key><term>coiled</term><term>serpent-coiled</term><term>serpentine</term></entry><entry><key>stigmata</key><term>wound</term><term>nail holes</term><term>martyr</term><term>martyrdom</term><term>saint</term><term>self-flagellant</term></entry><entry><key>stockings</key><term>socks</term><term>leggings</term></entry><entry><key>surprise</key><term>shock</term><term>fear</term><term>terror</term><term>amazement</term><term>wonder</term></entry><entry><key>swaddled</key><term>wrapped</term><term>swaddle</term><term>swaddling clothes</term><term>bundled</term><term>covered</term></entry><entry><key>tail</key><term>rear</term><term>behind</term></entry><entry><key>tarsus</key><term>foot</term><term>feet</term><term>ankle</term><term>heel</term></entry><entry><key>tears</key><term>tear</term><term>cry</term><term>crying</term><term>weeping</term></entry><entry><key>teeth</key><term>tooth</term></entry><entry><key>terror</key><term>fear</term><term>surprise</term><term>horror</term><term>dread</term><term>fright</term><term>panic</term></entry><entry><key>tights</key><term>breeches</term><term>shorts</term><term>pants</term><term>trousers</term><term>leggings</term><term>stockings</term></entry><entry><key>tongue</key></entry><entry><key>torture</key><term>pain</term><term>agony</term><term>anguish</term><term>persecution</term><term>torment</term><term>suffering</term></entry><entry><key>upper body</key><term>torso</term><term>midriff</term><term>chest</term><term>breast</term><term>breasts</term><term>bosom</term></entry><entry><key>veil</key><term>shroud</term><term>covering</term></entry><entry><key>veins</key><term>vein</term><term>artery</term><term>capillary</term><term>arteries</term><term>sinews</term></entry><entry><key>wing</key><term>bat-winged</term><term>wings</term><term>feather</term></entry><entry><key>womb</key><term>genitals</term><term>fetus</term><term>uterus</term><term>giving birth</term></entry><entry><key>young</key><term>youth</term><term>child</term><term>infant</term><term>baby</term><term>boy</term><term>girl</term></entry><entry><key>ant</key><term>ants</term><term>emmet</term><term>insect</term></entry><entry><key>antenna</key><term>antennae</term><term>feeler</term></entry><entry><key>ass</key><term>donkey</term></entry><entry><key>bat</key><term>bats</term><term>mammal</term></entry><entry><key>barking</key><term>howling</term></entry><entry><key>beak</key><term>beaks</term><term>bill</term></entry><entry><key>bee</key><term>hornet</term><term>insect bumblebee</term><term>wasp</term><term>bees</term></entry><entry><key>beetle</key><term>beetles</term><term>emmet</term><term>ant</term><term>fly</term><term>insect</term></entry><entry><key>Behemoth</key><term>giant</term><term>beast</term><term>monster</term></entry><entry><key>bird</key><term>birds</term><term>cuckoo</term><term>crane</term><term>dove</term><term>eagle</term><term>hawk</term><term>parrot</term><term>peacock</term><term>robin</term><term>sparrow</term><term>duck</term><term>stork</term><term>swan</term><term>wren</term><term>bluejay</term><term>blackbird</term><term>raven</term></entry><entry><key>butterfly</key><term>moth</term><term>insect</term></entry><entry><key>cat</key><term>cats</term><term>mammal</term><term>feline</term></entry><entry><key>caterpillar</key><term>insect</term><term>larva</term><term>inch-worm</term></entry><entry><key>centipede</key><term>millipede</term><term>insect</term></entry><entry><key>chrysalis</key><term>cocoon</term><term>sheath</term></entry><entry><key>coiled</key><term>spiral</term><term>loop</term><term>serpent-coiled</term><term>intertwined</term><term>curled</term></entry><entry><key>cow</key><term>bull</term><term>cows</term><term>mammal</term><term>ox</term><term>cattle</term></entry><entry><key>crab</key><term>crabs</term><term>lobster</term><term>shrimp</term></entry><entry><key>crane</key><term>heron</term><term>stork</term><term>bird</term></entry><entry><key>crest</key><term>ruff</term><term>comb</term><term>tuft</term><term>plume</term><term>crown</term></entry><entry><key>cuckoo</key><term>bird</term><term>cuckoos</term><term>various other spellings</term></entry><entry><key>deer</key><term>fawn</term><term>doe</term><term>buck</term><term>mammal</term><term>stag</term></entry><entry><key>dog</key><term>dogs</term><term>puppy</term><term>puppies</term><term>hound</term><term>barking</term><term>mammal</term></entry><entry><key>dove</key><term>bird</term></entry><entry><key>dragon</key><term>dragons</term><term>monster</term><term>wyvern</term></entry><entry><key>dragonfly</key><term>insect</term><term>fly</term></entry><entry><key>duck</key><term>bird</term><term>duckling</term><term>ducks</term></entry><entry><key>eagle</key><term>bird</term><term>eagles</term></entry><entry><key>eel</key><term>eels</term></entry><entry><key>emmet</key><term>ant</term><term>insect</term></entry><entry><key>fin</key><term>fins</term></entry><entry><key>fish</key></entry><entry><key>flock</key><term>sheep</term><term>shepherd</term><term>herd</term></entry><entry><key>fly</key><term>beetle</term><term>insect</term></entry><entry><key>flying</key><term>flight</term><term>hovering</term><term>rising</term><term>ascending</term><term>floating</term><term>soaring</term></entry><entry><key>fox</key><term>foxes</term><term>mammal</term></entry><entry><key>frog</key><term>toad</term><term>frogs</term><term>tadpole</term></entry><entry><key>fur</key><term>hide</term><term>pelt</term><term>wool</term><term>hair</term><term>coat</term></entry><entry><key>glow-worm</key><term>worm</term><term>inch-worm</term><term>caterpillar</term></entry><entry><key>grasshopper</key><term>cricket</term><term>insect</term><term>locust</term></entry><entry><key>grazing</key><term>eating</term><term>foraging</term><term>feeding</term></entry><entry><key>hawk</key><term>bird</term><term>buzzard</term><term>vulture</term><term>kite</term><term>falcon</term></entry><entry><key>hoof</key><term>hooves</term></entry><entry><key>horn</key><term>antler</term><term>tusk</term><term>horns</term><term>horned</term></entry><entry><key>hornet</key><term>bee</term><term>bumblebee</term><term>wasp</term><term>bees</term><term>hornets</term><term>insect</term></entry><entry><key>horse</key><term>mare</term><term>stallion</term><term>filly</term><term>steed</term><term>horses</term><term>mammal</term></entry><entry><key>inch-worm</key><term>worm</term><term>glow-worm</term><term>caterpillar</term></entry><entry><key>insect</key><term>bug</term><term>beetle</term><term>fly</term><term>ant</term><term>emmet</term><term>bee</term><term>hornet</term><term>wasp</term><term>spider</term><term>insects</term></entry><entry><key>Leviathan</key><term>giant</term><term>monster</term></entry><entry><key>lion</key><term>lioness</term><term>lions</term><term>mammal</term></entry><entry><key>lizard</key><term>chameleon</term><term>iguana</term><term>lizards</term></entry><entry><key>locust</key><term>insect</term><term>grasshopper</term><term>cicada</term></entry><entry><key>mammal</key><term>cow</term><term>cat</term><term>lion</term><term>fox</term><term>horse</term><term>deer</term><term>dog</term><term>mouse</term><term>sheep</term><term>squirrel</term><term>tiger</term><term>ram</term></entry><entry><key>mane</key></entry><entry><key>moth</key><term>butterfly</term><term>insect moths</term></entry><entry><key>mouse</key><term>mammal</term><term>rat</term><term>mice</term><term>rodent</term></entry><entry><key>owl</key><term>bird</term><term>owls</term></entry><entry><key>ox</key><term>oxen</term><term>cow</term><term>mammal</term></entry><entry><key>oyster</key><term>oysters</term></entry><entry><key>parrot</key><term>parrots</term><term>bird</term></entry><entry><key>paw</key><term>paws</term></entry><entry><key>peacock</key><term>bird</term><term>peacocks</term></entry><entry><key>perching</key><term>sitting</term><term>resting</term></entry><entry><key>pig</key><term>swine</term><term>hog</term><term>sow</term><term>boar</term></entry><entry><key>polypus</key><term>polyp</term><term>octopus</term><term>squid</term><term>cuttlefish</term></entry><entry><key>preying</key><term>prey</term><term>hunting</term><term>stalking</term><term>chasing</term></entry><entry><key>ram</key><term>sheep</term><term>mammal</term></entry><entry><key>rearing</key></entry><entry><key>reticulated</key><term>reticulation</term><term>net</term><term>netted</term><term>web</term></entry><entry><key>robin</key><term>bird</term></entry><entry><key>rooster</key><term>chicken</term><term>bird</term><term>cock</term><term>roosters</term></entry><entry><key>scales</key><term>scale</term></entry><entry><key>scorpion</key><term>scorpions</term></entry><entry><key>serpent</key><term>snake</term><term>serpent-coiled</term><term>snake-like</term><term>serpentine</term><term>viper</term></entry><entry><key>sheep</key><term>ram</term><term>mammal</term><term>lamb</term></entry><entry><key>shrimp</key><term>lobster</term></entry><entry><key>skin</key><term>hide</term><term>pelt</term><term>fur</term></entry><entry><key>snail</key><term>snails</term></entry><entry><key>snake</key><term>serpent</term><term>snake-like</term><term>serpentine</term><term>serpent-coiled</term><term>viper</term></entry><entry><key>sparrow</key><term>bird</term></entry><entry><key>spider</key><term>insect</term></entry><entry><key>squirrel</key><term>mammal</term><term>rodent</term></entry><entry><key>stag</key><term>deer</term><term>mammal</term><term>buck</term><term>roe</term></entry><entry><key>starfish</key></entry><entry><key>stork</key><term>bird</term></entry><entry><key>swan</key><term>bird</term></entry><entry><key>tail</key></entry><entry><key>talon</key><term>claw</term></entry><entry><key>tiger</key><term>mammal</term><term>tyger</term><term>tigress</term><term>tigers</term></entry><entry><key>toad</key><term>frog</term></entry><entry><key>unicorn</key><term>unicorns</term><term>horn</term></entry><entry><key>whelk</key><term>oyster</term><term>shell</term></entry><entry><key>wolf</key><term>mammal</term><term>wolves</term></entry><entry><key>worm</key><term>worms</term><term>glow-worm</term><term>inch-worm</term></entry><entry><key>wyvern</key><term>dragon</term><term>wyverns</term></entry><entry><key>acorn</key><term>oak</term></entry><entry><key>amaryllis</key><term>flower</term></entry><entry><key>anemone</key><term>anemone pulsatilla</term><term>seaweed</term></entry><entry><key>anemone pulsatilla</key><term>anemone</term><term>seaweed</term></entry><entry><key>anthropomorphic</key><term>anthropoid</term><term>humanlike</term></entry><entry><key>apple</key><term>fruit</term></entry><entry><key>arching</key><term>arch</term><term>arcing</term></entry><entry><key>barren</key><term>wilderness</term><term>dry</term><term>blighted</term><term>arid</term><term>desolate</term><term>sterile</term><term>waste</term><term>infertile</term></entry><entry><key>berry</key><term>fruit</term></entry><entry><key>birch</key><term>tree</term></entry><entry><key>blight</key><term>disease</term><term>plague</term><term>affliction</term><term>scourge</term></entry><entry><key>blossom</key><term>flower</term><term>bud</term><term>petal</term></entry><entry><key>branch</key><term>tree</term><term>bough</term><term>limb</term></entry><entry><key>bud</key><term>flower</term><term>blossom</term><term>petal</term></entry><entry><key>catchfly</key><term>flower</term></entry><entry><key>catkin</key></entry><entry><key>corpse-plant</key><term>flower</term></entry><entry><key>cypress</key><term>tree</term></entry><entry><key>date</key><term>fruit</term></entry><entry><key>Dodacatheon</key></entry><entry><key>fallen</key><term>dropped</term></entry><entry><key>fig</key><term>fruit</term></entry><entry><key>flame-like</key><term>fiery</term><term>fire</term></entry><entry><key>flower</key><term>blossom</term><term>bud</term><term>petal</term><term>lilly</term><term>Lilly of Havilah</term><term>marigold</term><term>sunflower</term><term>amarylis</term><term>catchfly</term><term>corpse-plant</term><term>gloriosa superba</term><term>meadia</term><term>monotropa</term><term>pasqueflower</term><term>pomegranate</term><term>poppy</term><term>plant</term></entry><entry><key>fruit</key><term>apple</term><term>grape</term><term>mandrake</term><term>fig</term><term>date</term><term>berry</term></entry><entry><key>gloriosa superba</key><term>flower</term></entry><entry><key>grain</key><term>grain stem</term><term>grain tassel</term></entry><entry><key>grain stem</key><term>grain</term><term>grain tassel</term></entry><entry><key>grain tassel</key><term>grain stem</term><term>grain</term></entry><entry><key>grape</key><term>fruit</term></entry><entry><key>grass</key><term>reed</term><term>meadow</term><term>pasture</term><term>lawn</term></entry><entry><key>hedge</key><term>bush</term><term>bushes</term><term>privet</term><term>thicket</term></entry><entry><key>indeterminate</key><term>indefinite</term><term>uncertain</term><term>undefined</term><term>borderless</term></entry><entry><key>intertwined</key><term>coiled</term><term>serpent-coiled</term><term>spiral</term><term>loop</term><term>twisted</term><term>tangled</term><term>entwined</term></entry><entry><key>ivy</key><term>leaf</term><term>plant</term><term>vine</term></entry><entry><key>leaf</key><term>foliage</term></entry><entry><key>leafless</key><term>bare</term></entry><entry><key>lichens</key><term>lichen</term><term>moss</term><term>scales</term></entry><entry><key>lily</key><term>lilly</term><term>flower</term><term>blossom</term><term>Lilly of Havilah</term><term>St. Bernard's Lilly</term></entry><entry><key>Lilly of Havilah</key><term>lily</term></entry><entry><key>loop</key><term>spiral</term><term>coiled</term><term>intertwined</term><term>twisted</term><term>curled</term></entry><entry><key>mandrake</key><term>fruit</term><term>root</term><term>plant</term></entry><entry><key>marigold</key><term>flower</term></entry><entry><key>Meadia</key><term>flower</term></entry><entry><key>monotropa</key><term>flower</term></entry><entry><key>mushroom</key><term>toadstool</term></entry><entry><key>moss</key><term>seaweed</term><term>lichens</term></entry><entry><key>oak</key><term>acorn</term><term>tree</term></entry><entry><key>palm</key><term>tree</term></entry><entry><key>pasqueflower</key><term>flower</term></entry><entry><key>petal</key><term>bud</term><term>blossom</term><term>flower</term></entry><entry><key>pine</key><term>tree</term></entry><entry><key>plant</key><term>flower</term><term>shrub</term><term>bush</term><term>ivy</term></entry><entry><key>pomegranate</key><term>fruit</term></entry><entry><key>poppy</key><term>flower</term></entry><entry><key>reed</key><term>grass</term><term>stem</term></entry><entry><key>root</key><term>tuber</term></entry><entry><key>rose</key><term>flower</term><term>blossom</term></entry><entry><key>St. Bernard's Lilly</key><term>lily</term><term>lilly</term><term>Lilly of Havilah</term></entry><entry><key>seaweed</key><term>anemone</term><term>anemone pulsatilla</term><term>moss</term></entry><entry><key>snake-like</key><term>snake</term><term>serpent-coiled</term><term>serpent</term><term>serpentine</term></entry><entry><key>stamen</key></entry><entry><key>stump</key></entry><entry><key>sunflower</key><term>flower</term></entry><entry><key>thistle</key><term>plant</term><term>thorn</term><term>spiky</term></entry><entry><key>thorn</key><term>plant</term><term>thistle</term><term>spiky</term></entry><entry><key>thyme</key><term>herb</term><term>herbs</term></entry><entry><key>tree</key><term>willow</term><term>stump</term><term>root</term><term>trunk</term><term>pine</term><term>palm</term><term>oak</term><term>birch</term><term>cypress</term><term>branch</term></entry><entry><key>Tree of Jesse</key></entry><entry><key>trunk</key><term>tree trunk</term></entry><entry><key>vallisneria spiralis</key><term>plant</term><term>seaweed</term></entry><entry><key>vine</key><term>grape</term><term>plant</term><term>ivy</term></entry><entry><key>wilderness</key><term>desert</term><term>forest</term><term>waste land</term><term>wild</term></entry><entry><key>willow</key><term>tree</term></entry><entry><key>air</key><term>vapor</term><term>sky</term><term>wind</term></entry><entry><key>altar</key><term>pyre</term><term>bier</term><term>shrine</term></entry><entry><key>anvil</key><term>anvils</term></entry><entry><key>apron</key><term>aprons</term><term>smock</term></entry><entry><key>ark</key><term>arks</term><term>boat</term><term>ship</term><term>vessel</term></entry><entry><key>Arnon</key><term>river</term></entry><entry><key>arrow</key><term>dart</term><term>arrows</term></entry><entry><key>Athens</key><term>city</term></entry><entry><key>Atlantic</key><term>sea</term><term>ocean</term></entry><entry><key>backpack</key><term>bundle</term><term>bag</term><term>pack</term></entry><entry><key>bag</key><term>backpack</term><term>bundle</term><term>pack</term><term>sack</term><term>pouch</term><term>satchel</term></entry><entry><key>ball</key><term>balls</term></entry><entry><key>bank</key><term>river bank</term><term>shore</term><term>edge</term></entry><entry><key>banner</key><term>banners</term><term>flag</term></entry><entry><key>barn</key><term>barns</term><term>stable</term></entry><entry><key>basket</key><term>baskets</term></entry><entry><key>bat</key><term>bats</term><term>bat-winged</term><term>stick</term></entry><entry><key>beads</key><term>jewelry</term><term>bead</term><term>rosary</term></entry><entry><key>beams of light</key><term>radiance</term></entry><entry><key>bed</key><term>cradle</term><term>beds</term></entry><entry><key>bell</key><term>bells</term></entry><entry><key>bellows</key></entry><entry><key>bier</key><term>altar</term><term>support</term></entry><entry><key>birdbath</key><term>bathing</term></entry><entry><key>blanket</key><term>cover</term><term>sheet</term></entry><entry><key>blood</key></entry><entry><key>blotch</key><term>spot</term><term>blight</term><term>smudge</term><term>blemish</term><term>blot</term><term>mark</term><term>stain</term></entry><entry><key>boat</key><term>ship</term><term>ark</term><term>vessel</term></entry><entry><key>book</key><term>Book of Brass</term><term>volume</term><term>manuscript</term></entry><entry><key>Book of Brass</key><term>book</term></entry><entry><key>bow</key><term>prow</term><term>front</term></entry><entry><key>bowl</key><term>chalice</term><term>cup</term><term>goblet</term><term>glass</term><term>plate</term><term>dish</term></entry><entry><key>bracelet</key><term>jewelry</term><term>ornament</term></entry><entry><key>bread</key><term>food</term></entry><entry><key>Britain</key><term>England</term><term>Albion</term></entry><entry><key>brush</key><term>combing</term><term>comb</term></entry><entry><key>bubbles</key></entry><entry><key>bundle</key><term>bag</term><term>backpack</term><term>sack</term><term>pack</term></entry><entry><key>bust</key><term>statue</term><term>effigy</term></entry><entry><key>Caithness</key></entry><entry><key>candlestick</key><term>candle</term></entry><entry><key>cannon</key><term>cannonball</term><term>artillery</term><term>gun</term></entry><entry><key>cannonball</key><term>cannon</term><term>ball</term></entry><entry><key>carpet</key><term>rug</term></entry><entry><key>cave</key><term>caves</term><term>cavern</term><term>den</term><term>hollow</term></entry><entry><key>chain</key><term>shackle</term><term>Chain of Jealousy</term><term>leash</term><term>bond</term><term>manacle</term></entry><entry><key>Chain of Jealousy</key></entry><entry><key>chair</key><term>seat</term><term>throne</term><term>couch</term><term>rocker</term></entry><entry><key>Chaldea</key></entry><entry><key>chalice</key><term>bowl</term><term>cup</term><term>goblet</term><term>glass</term><term>grail</term></entry><entry><key>chaos</key><term>void</term><term>disorder</term><term>tumult</term><term>turmoil</term><term>discord</term></entry><entry><key>chariot</key><term>chariots</term><term>carriage</term><term>coach</term></entry><entry><key>Chichester</key><term>city</term><term>town</term></entry><entry><key>circle</key><term>sphere</term><term>disc</term><term>orb</term><term>globe</term><term>ring</term></entry><entry><key>city</key><term>town</term><term>Dover</term><term>Athens</term><term>Chichester</term><term>London</term><term>Durness</term><term>Felpham</term><term>Jericho</term><term>Rome</term><term>York</term></entry><entry><key>cliff</key><term>Dover</term><term>bluff</term><term>precipice</term></entry><entry><key>clothing</key><term>shirt</term><term>gown</term><term>robe</term><term>skirt</term><term>breeches</term><term>stockings</term><term>coat</term><term>cloak</term><term>hood</term><term>clothes</term><term>attire</term><term>garments</term></entry><entry><key>cloud</key><term>clouds</term></entry><entry><key>coal</key><term>coals</term><term>cinder</term></entry><entry><key>coffin</key><term>coffin lid</term><term>casket</term></entry><entry><key>coffin lid</key><term>coffin</term></entry><entry><key>cog</key><term>cogs</term><term>gear</term></entry><entry><key>coil</key><term>coiled</term><term>serpent-coiled</term><term>loop</term><term>spiral</term><term>serpentine</term><term>twisted</term><term>helix</term></entry><entry><key>coin</key><term>money</term></entry><entry><key>collar</key></entry><entry><key>comb</key><term>combing</term><term>brush</term></entry><entry><key>comet</key><term>meteor</term><term>falling star</term></entry><entry><key>compasses</key><term>dividers</term><term>geometry</term></entry><entry><key>constellation</key><term>Pleiades</term><term>star</term><term>Orions belt</term><term>zodiac</term></entry><entry><key>couch</key><term>seat</term><term>chair</term></entry><entry><key>crack</key><term>crevice</term><term>chink</term><term>fissure</term><term>gap</term><term>split</term></entry><entry><key>cradle</key><term>rocking</term><term>bed</term><term>manger</term><term>crib</term></entry><entry><key>crescent</key><term>moon</term></entry><entry><key>cross</key><term>crucified</term><term>crucifix</term></entry><entry><key>crown</key><term>king</term><term>coronet</term></entry><entry><key>crutch</key><term>staff</term><term>crutches</term><term>lame</term><term>support</term></entry><entry><key>curtain</key><term>shroud</term><term>drapery</term><term>cloth</term><term>sheet</term><term>veil</term><term>screen</term></entry><entry><key>cymbal</key></entry><entry><key>dagger</key><term>knife</term><term>haft</term><term>sword</term></entry><entry><key>dark</key><term>darkness</term><term>shadow</term><term>night</term><term>eclipse</term><term>dusk</term><term>gloom</term><term>shade</term><term>black</term><term>dim</term></entry><entry><key>darkness</key><term>dark</term><term>shadow</term><term>night</term><term>eclipse</term><term>dusk</term><term>gloom</term><term>shade</term><term>black</term><term>dim</term></entry><entry><key>dart</key><term>arrow</term></entry><entry><key>Dead Sea</key><term>sea</term></entry><entry><key>decalogue</key><term>Hebrew letters</term><term>Old Testament</term><term>ten commandments</term></entry><entry><key>backward writing</key><term>backwards writing</term><term>mirror writing</term><term>mirror-writing</term></entry><entry><key>diagram</key><term>geometry</term><term>picture</term><term>drawing</term><term>design</term></entry><entry><key>distaff</key><term>spinning wheel</term><term>spindle</term><term>shuttle</term></entry><entry><key>dividers</key><term>pair of balances</term><term>compass</term><term>compasses</term></entry><entry><key>door</key><term>doorway</term><term>entrance</term><term>entry</term><term>entryway</term><term>gate</term><term>gateway</term><term>portal</term></entry><entry><key>Dover</key><term>cliff</term><term>city</term><term>town</term></entry><entry><key>Durness</key><term>city</term><term>town</term></entry><entry><key>earring</key><term>earing</term><term>ear</term><term>jewelry</term></entry><entry><key>earth</key><term>planet</term><term>globe</term><term>world</term><term>sphere</term><term>ground</term><term>soil</term><term>land</term></entry><entry><key>eclipse</key></entry><entry><key>effigy</key><term>statue</term><term>bust</term><term>likeness</term></entry><entry><key>egg</key></entry><entry><key>etching needle</key><term>graver</term><term>needle</term></entry><entry><key>eye</key><term>eye socket</term><term>eyeball</term></entry><entry><key>eye socket</key><term>eye</term></entry><entry><key>feather</key><term>quill</term><term>plume</term><term>feathers</term></entry><entry><key>Felpham</key><term>city</term><term>town</term></entry><entry><key>fire</key><term>flame-like</term><term>flame</term><term>flames</term><term>inferno</term></entry><entry><key>flag</key><term>flagpole</term><term>banner</term></entry><entry><key>flagpole</key><term>flag</term></entry><entry><key>fleur-de-lis</key></entry><entry><key>furnace</key><term>forge</term><term>smithy</term></entry><entry><key>geometry</key><term>diagram</term><term>triangle</term><term>circle</term><term>compasses</term></entry><entry><key>glass</key><term>goblet</term><term>chalice</term><term>cup</term></entry><entry><key>globe</key><term>earth</term><term>circle</term><term>planet</term><term>sphere</term><term>disc</term><term>orb</term></entry><entry><key>goblet</key><term>chalice</term><term>cup</term><term>glass</term></entry><entry><key>graphite pencil</key><term>pencil</term><term>pencils</term></entry><entry><key>grave</key><term>graveyard</term><term>tombstone</term><term>tomb</term><term>crypt</term></entry><entry><key>graver</key><term>etching needle</term></entry><entry><key>graveyard</key><term>grave</term><term>cemetery</term><term>burial</term><term>tombstone</term></entry><entry><key>haft</key><term>handle</term><term>hilt</term><term>shaft</term></entry><entry><key>hail</key><term>sleet</term><term>storm</term></entry><entry><key>hammer</key></entry><entry><key>handle</key><term>haft</term><term>shaft</term></entry><entry><key>harness</key><term>rein</term></entry><entry><key>harp</key></entry><entry><key>hat</key><term>cap (should be listed under "clothing")</term><term>helmet</term></entry><entry><key>heaven</key><term>sky</term><term>paradise</term></entry><entry><key>Hebrew letters</key><term>decalogue</term><term>Old Testament</term></entry><entry><key>hell</key><term>hades</term><term>inferno</term><term>abyss</term></entry><entry><key>hieroglyphic</key><term>diagram</term><term>hieroglyph</term></entry><entry><key>hill</key><term>mound</term><term>knoll</term></entry><entry><key>hinge</key><term>joint</term><term>axis</term><term>pivot</term></entry><entry><key>hook</key></entry><entry><key>hoop</key><term>circle</term><term>loop</term></entry><entry><key>horn</key><term>horned</term><term>antler</term><term>trumpet</term></entry><entry><key>inscription</key><term>Hebrew Letters</term><term>imprint</term><term>engraving</term><term>message</term><term>caption</term></entry><entry><key>iron</key><term>metal</term></entry><entry><key>island</key><term>peninsula</term><term>isle</term></entry><entry><key>Jericho</key><term>city</term></entry><entry><key>jewelry</key><term>necklace</term><term>earring</term><term>bracelet</term><term>beads</term><term>pearl</term><term>brooch</term></entry><entry><key>Jordan River</key><term>river</term></entry><entry><key>key</key><term>keys</term></entry><entry><key>kite</key></entry><entry><key>knife</key><term>dagger</term><term>haft</term><term>sword</term><term>blade</term></entry><entry><key>knot</key><term>skein</term><term>tangle</term><term>tie</term><term>bond</term></entry><entry><key>ladder</key></entry><entry><key>lake</key></entry><entry><key>Lambeth</key></entry><entry><key>lamp</key><term>light</term><term>lantern</term></entry><entry><key>leash</key><term>rein</term><term>chain</term><term>rope</term></entry><entry><key>light</key><term>sun</term><term>lamp</term><term>radiance</term><term>halo</term><term>ray</term><term>illumination</term></entry><entry><key>lightning</key><term>storm</term><term>bolt</term></entry><entry><key>line</key><term>mark</term><term>stripe</term><term>text</term><term>cord</term><term>band</term></entry><entry><key>liquid</key><term>water</term><term>fluid</term></entry><entry><key>London</key><term>city</term></entry><entry><key>Lizard Point</key></entry><entry><key>lyre</key></entry><entry><key>mandolin</key><term>guitar</term></entry><entry><key>manger</key><term>cradle</term><term>stable</term></entry><entry><key>mantel</key><term>fireplace</term></entry><entry><key>map</key></entry><entry><key>marble</key><term>stone</term></entry><entry><key>mark</key><term>line</term><term>trace</term><term>spot</term><term>blemish</term><term>stain</term><term>stripe</term></entry><entry><key>mat</key><term>covering</term></entry><entry><key>moon</key><term>crescent</term><term>orb</term></entry><entry><key>mound</key><term>hill</term><term>pile</term></entry><entry><key>mountain</key><term>hill</term><term>mountains</term><term>cliff</term><term>peak</term><term>ridge</term></entry><entry><key>nail</key></entry><entry><key>necklace</key><term>jewelry</term><term>beads</term></entry><entry><key>nest</key></entry><entry><key>net</key><term>reticulated</term><term>web</term><term>netting</term></entry><entry><key>Net of Religion</key></entry><entry><key>night</key><term>dark</term><term>darkness</term><term>moon</term><term>star</term><term>sunset</term><term>black</term></entry><entry><key>note (musical)</key><term>notes</term></entry><entry><key>Old Testament</key><term>Bible</term><term>Pentateuch</term><term>Torah</term><term>Decalogue</term><term>Hebrew letters</term></entry><entry><key>open</key><term>plain</term></entry><entry><key>Orion's belt</key><term>constellation</term><term>star</term></entry><entry><key>page</key><term>paper</term><term>sheet</term><term>leaf</term></entry><entry><key>pair of balances</key><term>scales</term><term>dividers</term><term>compasses</term><term>compass</term></entry><entry><key>palette</key></entry><entry><key>palmette</key><term>palm</term></entry><entry><key>paper</key><term>page</term><term>scroll</term><term>sheet</term><term>leaf</term></entry><entry><key>Parthia</key></entry><entry><key>path</key><term>road</term><term>trail</term><term>route</term><term>course</term><term>footpath</term></entry><entry><key>pearl</key><term>jewelry</term><term>jewel</term></entry><entry><key>pedestal</key><term>plinth</term><term>base</term></entry><entry><key>pen</key><term>quill</term><term>etching needle</term><term>pencil</term></entry><entry><key>peninsula</key></entry><entry><key>Pentland</key></entry><entry><key>pickax</key><term>ax</term></entry><entry><key>picture</key><term>drawing</term><term>painting</term><term>image</term><term>design</term></entry><entry><key>pillow</key><term>cushion</term></entry><entry><key>pipe</key></entry><entry><key>pitcher</key><term>cup</term><term>chalice</term><term>glass</term><term>jug</term><term>container</term><term>vessel</term></entry><entry><key>plague</key><term>disease</term><term>affliction</term><term>epidemic</term><term>contagion</term></entry><entry><key>plain</key><term>plains</term><term>field</term><term>grass</term><term>open</term><term>lawn</term><term>meadow</term><term>moor</term></entry><entry><key>planet</key><term>star</term><term>earth</term><term>sphere</term><term>globe</term><term>world</term><term>orb</term></entry><entry><key>plate</key><term>platter</term><term>dish</term></entry><entry><key>Pleiades</key><term>constellation</term><term>star</term></entry><entry><key>plinth</key><term>pedestal</term></entry><entry><key>plow</key><term>plowing</term></entry><entry><key>plume</key><term>feather</term><term>quill</term><term>crest</term></entry><entry><key>poison</key><term>poisonous</term><term>venom</term></entry><entry><key>pole</key><term>staff</term><term>stick</term><term>rod</term><term>beam</term></entry><entry><key>pot</key><term>vessel</term><term>cauldron</term></entry><entry><key>purse</key><term>sack</term><term>tote</term><term>pouch</term></entry><entry><key>quill</key><term>plume</term><term>pen</term><term>feather</term></entry><entry><key>quiver</key></entry><entry><key>racquet</key><term>racquets</term></entry><entry><key>radiance</key><term>beams of light</term><term>light</term><term>sun</term><term>brightness</term><term>luminescence</term><term>brilliance</term><term>glow</term><term>shine</term></entry><entry><key>rain</key><term>sleet</term><term>rainbow</term><term>storm</term><term>shower</term><term>deluge</term></entry><entry><key>rainbow</key><term>rain</term><term>rainbows</term></entry><entry><key>rein</key><term>reins</term><term>harness</term><term>leash</term><term>bridle</term></entry><entry><key>ring</key><term>circle</term><term>halo</term><term>loop</term></entry><entry><key>river</key><term>stream</term><term>creek</term></entry><entry><key>road</key><term>street</term><term>path</term><term>trail</term><term>route</term><term>course</term></entry><entry><key>rocker</key><term>chair</term></entry><entry><key>rod</key><term>pole</term><term>staff</term><term>stick</term><term>scepter</term><term>sceptre</term><term>bar</term><term>wand</term></entry><entry><key>roller</key><term>waves</term><term>sea</term><term>wave</term><term>breaker</term><term>crest</term></entry><entry><key>Rome</key><term>city</term></entry><entry><key>rope</key><term>trace</term><term>string</term><term>cord</term><term>line</term></entry><entry><key>sand</key><term>beach</term><term>dirt</term></entry><entry><key>scales</key><term>pair of balances</term><term>balance</term></entry><entry><key>scepter</key><term>staff</term><term>rod</term><term>stick</term><term>wand</term><term>sceptre</term><term>baton</term></entry><entry><key>scissors</key><term>clippers</term><term>shears</term></entry><entry><key>scroll</key><term>paper</term><term>manuscript</term><term>parchment</term><term>scripture</term></entry><entry><key>scythe</key><term>harvesting</term><term>sickle</term><term>blade</term><term>reaper</term></entry><entry><key>sea</key><term>ocean</term><term>shore</term><term>waves</term><term>water</term><term>roller</term><term>beach</term></entry><entry><key>sea of time and space</key><term>sea</term><term>ocean of time and space</term></entry><entry><key>seat</key><term>chair</term><term>sitting</term><term>rocker</term></entry><entry><key>serpentine</key><term>serpent</term><term>snake</term><term>dragon</term><term>coil</term><term>coiled</term><term>serpent-coiled</term><term>loop</term><term>twisted</term><term>spiral</term><term>helix</term></entry><entry><key>shackle</key><term>chain</term><term>bound</term><term>leash</term><term>manacle</term></entry><entry><key>shadow</key><term>shadows</term><term>dark</term><term>darkness</term><term>night</term><term>eclipse</term><term>shade</term></entry><entry><key>sheath</key><term>sheathing</term><term>case</term><term>scabbard</term><term>covering</term></entry><entry><key>sheet</key><term>drapery</term><term>curtain</term><term>shroud</term><term>fabric</term></entry><entry><key>shell</key><term>whelk</term><term>shells</term></entry><entry><key>shepherd's crook</key><term>staff</term><term>walking stick</term></entry><entry><key>shield</key><term>armor</term></entry><entry><key>ship</key><term>boat</term><term>sailing</term><term>ark</term><term>shuttle</term><term>vessel</term></entry><entry><key>shoe</key><term>shoes</term><term>sandal</term></entry><entry><key>shore</key><term>bank</term><term>sand</term><term>beach</term><term>coast</term><term>waterfront</term></entry><entry><key>shuttle</key><term>spinning wheel</term><term>distaff</term></entry><entry><key>shuttlecock</key><term>birdie</term></entry><entry><key>skein</key><term>knot</term><term>twisted</term><term>tangle</term></entry><entry><key>skull</key><term>bone</term><term>head</term></entry><entry><key>sky</key><term>air</term><term>heaven</term></entry><entry><key>sleet</key><term>storm</term><term>snow</term><term>rain</term><term>ice</term></entry><entry><key>smoke</key><term>soot</term><term>vapor</term></entry><entry><key>snow</key><term>storm</term></entry><entry><key>soot</key><term>smoke</term></entry><entry><key>spear</key><term>lance</term></entry><entry><key>spectacles</key><term>eyeglasses</term></entry><entry><key>sphere</key><term>globe</term><term>planet</term><term>earth</term><term>world</term><term>orb</term></entry><entry><key>spike</key><term>spiky</term></entry><entry><key>spiky</key><term>spike</term><term>sharp</term></entry><entry><key>spindle</key><term>spinning wheel</term><term>distaff</term><term>shuttle</term></entry><entry><key>spinning wheel</key><term>spindle</term><term>distaff</term><term>shuttle</term></entry><entry><key>spiral</key><term>loop</term><term>coil</term><term>helix</term></entry><entry><key>staff</key><term>walking stick</term><term>shepherds crook</term><term>crutch</term><term>pole</term><term>rod</term></entry><entry><key>star</key><term>planet</term><term>Pleiades</term><term>constellation</term><term>night</term><term>stars</term></entry><entry><key>star of Bethlehem</key><term>star</term></entry><entry><key>statue</key><term>bust</term><term>effigy</term></entry><entry><key>stick</key><term>pole</term><term>staff</term><term>rod</term><term>branch</term><term>bough</term></entry><entry><key>stone</key><term>rock</term><term>boulder</term><term>London Stone</term></entry><entry><key>stool</key><term>chair</term></entry><entry><key>storm</key><term>whirlwind</term><term>sleet</term><term>rain</term><term>snow</term><term>blizzard</term><term>tempest</term><term>gale</term></entry><entry><key>straw</key><term>fibre</term><term>hay</term></entry><entry><key>stream</key><term>river</term><term>creek</term><term>brook</term></entry><entry><key>streams of gore</key></entry><entry><key>string</key><term>rope</term><term>trace</term><term>line</term><term>fibre</term><term>thread</term><term>cord</term></entry><entry><key>stripe</key><term>line</term><term>mark</term><term>striped</term><term>stripes</term></entry><entry><key>sun</key><term>sphere</term><term>light</term><term>radiance</term><term>sunrise</term><term>sunset</term></entry><entry><key>sunrise</key><term>sunset</term><term>sun</term></entry><entry><key>sunset</key><term>sunrise</term><term>sun</term></entry><entry><key>sword</key><term>dagger</term><term>haft</term><term>knife</term><term>saber</term></entry><entry><key>table</key></entry><entry><key>tablet</key><term>book</term></entry><entry><key>tambourine</key></entry><entry><key>text</key><term>book</term><term>tablet</term><term>line</term><term>words</term></entry><entry><key>thread</key><term>string</term><term>fibre</term></entry><entry><key>throne</key><term>seat</term><term>chair</term></entry><entry><key>tongs</key></entry><entry><key>trace</key><term>rope</term><term>mark</term></entry><entry><key>trilithon</key><term>Stonehenge</term><term>ruin</term></entry><entry><key>tombstone</key><term>grave</term><term>gravestone</term><term>marker</term></entry><entry><key>triangle</key><term>geometry</term></entry><entry><key>trumpet</key><term>horn</term><term>trumpeter</term><term>bugle</term></entry><entry><key>Ulro</key></entry><entry><key>valley</key><term>vale</term><term>dale</term><term>lowland</term></entry><entry><key>vapor</key><term>air</term><term>mist</term><term>fog</term><term>smoke</term></entry><entry><key>vase</key><term>vial</term><term>vessel</term></entry><entry><key>Venus</key><term>Aphrodite</term><term>planet</term><term>star</term></entry><entry><key>vial</key><term>vase</term><term>vessel</term></entry><entry><key>violin</key><term>fiddle</term></entry><entry><key>void</key><term>chaos</term><term>space</term><term>emptiness</term></entry><entry><key>wake</key><term>waves</term><term>roller</term></entry><entry><key>walking stick</key><term>staff</term><term>walking</term><term>shepherds crook</term></entry><entry><key>water</key><term>liquid</term><term>sea</term><term>rain</term><term>fluid</term></entry><entry><key>waterfall</key><term>cataract</term><term>cascade</term></entry><entry><key>water spout</key><term>geyser</term><term>fountain</term></entry><entry><key>waves</key><term>sea</term><term>wake</term><term>roller</term></entry><entry><key>web</key><term>reticulated</term><term>net</term><term>netting</term><term>weave</term><term>tangle</term></entry><entry><key>weight</key><term>pair of balances</term><term>scales</term><term>dividers</term><term>load</term><term>burden</term></entry><entry><key>wheel</key><term>wheels</term></entry><entry><key>whip</key><term>whipping</term><term>switch</term><term>scourge</term></entry><entry><key>whirlwind</key><term>wind</term><term>storm</term><term>tornado</term><term>tempest</term><term>cyclone</term></entry><entry><key>wicker</key><term>straw-woven</term></entry><entry><key>wig</key><term>hair</term><term>hairpiece</term></entry><entry><key>will o' the wisp</key><term>radiance</term><term>light</term><term>glow</term><term>illusion</term></entry><entry><key>wind</key><term>whirlwind</term><term>air</term><term>gale</term><term>breeze</term><term>tempest</term><term>gust</term></entry><entry><key>wine</key><term>chalice</term><term>goblet</term></entry><entry><key>wing</key><term>wings</term><term>pinion</term></entry><entry><key>wood</key><term>tree</term><term>trunk</term><term>oak</term><term>birch</term><term>willow</term><term>trunk</term><term>branch</term><term>stick</term><term>wilderness</term><term>beam forest</term></entry><entry><key>yoke</key><term>harness</term><term>bond</term></entry><entry><key>York</key><term>city</term><term>town</term></entry><entry><key>altar</key><term>bier</term><term>shrine</term></entry><entry><key>arch</key><term>arching</term><term>dome</term><term>curve</term><term>vault</term><term>archway</term></entry><entry><key>beam</key><term>rafter</term><term>lintel</term><term>pillar</term><term>support</term></entry><entry><key>brick</key><term>bricks</term><term>block</term></entry><entry><key>building</key><term>house</term><term>church</term><term>tower</term><term>hut</term><term>structure</term></entry><entry><key>cell</key><term>prison</term><term>chamber</term><term>room</term><term>dungeon</term></entry><entry><key>chamber</key><term>room</term><term>cell</term><term>bedroom</term></entry><entry><key>chimney</key><term>smoke stack</term><term>smokestack</term><term>fireplace</term></entry><entry><key>church</key><term>St. Paul's Cathedral</term><term>Westminster Abbey</term><term>temple</term><term>spire</term><term>building</term><term>chapel</term><term>cathedral</term><term>steeple</term></entry><entry><key>classical art</key></entry><entry><key>cottage</key><term>house</term><term>hut</term><term>building</term><term>cabin</term><term>home</term></entry><entry><key>dome</key><term>arch</term><term>roof</term><term>vault</term><term>cupola</term></entry><entry><key>door</key><term>doorway</term><term>entrance</term><term>entry</term><term>entryway</term><term>gate</term><term>gateway</term><term>portal [this word appears under objects as well]</term></entry><entry><key>facade</key><term>pilaster</term><term>front</term></entry><entry><key>fence</key><term>wall</term><term>barrier</term></entry><entry><key>fireplace</key><term>furnace</term><term>mantel</term><term>chimney</term><term>hearth</term></entry><entry><key>floor</key><term>ground</term></entry><entry><key>garden</key></entry><entry><key>Gothic art</key></entry><entry><key>grate</key><term>vent</term></entry><entry><key>house</key><term>cottage</term><term>hut</term><term>building</term><term>home</term></entry><entry><key>hut</key><term>cottage</term><term>building</term><term>house</term><term>cabin</term></entry><entry><key>lintel</key><term>pilaster</term><term>beam</term></entry><entry><key>London Stone</key><term>stone</term><term>rock</term></entry><entry><key>menhir</key><term>ruin</term><term>pillar</term><term>Stonehenge</term><term>monolith</term><term>monument</term></entry><entry><key>mine</key><term>tunnel</term><term>mineshaft</term></entry><entry><key>pilaster</key><term>pillar</term><term>lintel</term><term>column</term><term>support</term></entry><entry><key>pillar</key><term>menhir</term><term>pilaster</term><term>pillars</term><term>support</term></entry><entry><key>plinth</key><term>pedestal</term></entry><entry><key>post</key><term>pillar</term><term>support</term><term>column</term></entry><entry><key>prison</key><term>cell</term><term>dungeon</term><term>jail</term></entry><entry><key>pyramid</key><term>monument</term></entry><entry><key>rafter</key><term>beam</term><term>pillar</term><term>support</term><term>crosspiece</term></entry><entry><key>roof</key><term>ceiling</term><term>dome</term></entry><entry><key>room</key><term>chamber</term><term>cell</term></entry><entry><key>ruin</key><term>trilithon</term><term>Stonehenge</term><term>ruins</term></entry><entry><key>St. Paul's Cathedral</key><term>church</term><term>building</term><term>cathedral</term></entry><entry><key>spire</key><term>turret</term><term>tower</term><term>church</term><term>steeple</term></entry><entry><key>stable</key><term>stall</term><term>stables</term></entry><entry><key>stairs</key><term>step</term><term>stairway</term><term>staircase</term><term>steps</term></entry><entry><key>step</key><term>stairs</term></entry><entry><key>Stonehenge</key><term>trilithon</term><term>ruin</term><term>menhir</term><term>pillar</term></entry><entry><key>street</key><term>path</term><term>road</term></entry><entry><key>temple</key><term>church</term><term>building</term><term>chapel</term><term>temples</term></entry><entry><key>tent</key><term>tents</term><term>tomb canopy</term><term>shelter</term></entry><entry><key>tomb</key><term>grave</term><term>gravestone</term><term>tomb canopy</term><term>mausoleum</term><term>sepulcher</term></entry><entry><key>tomb canopy</key><term>tent</term><term>shroud</term></entry><entry><key>tombstone</key><term>grave</term><term>gravestone</term><term>grave stone</term><term>head stone</term><term>headstone</term></entry><entry><key>tower</key><term>turret</term><term>spire</term><term>building</term><term>steeple</term><term>towers</term></entry><entry><key>tracery</key><term>window</term></entry><entry><key>trilithon</key><term>Stonehenge</term><term>ruin</term></entry><entry><key>tunnel</key><term>tunnels</term><term>mine</term><term>passage</term><term>shaft</term></entry><entry><key>turret</key><term>tower</term><term>spire</term><term>battlement</term><term>steeple</term></entry><entry><key>wall</key><term>walls</term></entry><entry><key>Westminster Abbey</key><term>church</term></entry><entry><key>window</key><term>windows</term><term>tracery</term><term>stained glass</term></entry></thesaurus>